systole/__init__.py
systole/correction.py
systole/detection.py
systole/hrv.py
systole/io.py
systole/recording.py
systole/utils.py
systole/datasets/__init__.py
systole/detectors/__init__.py
systole/detectors/christov.py
systole/detectors/engelse_zeelenberg.py
systole/detectors/hamilton.py
systole/detectors/moving_average.py
systole/detectors/msptd.py
systole/detectors/pan_tompkins.py
systole/detectors/rolling_average_ppg.py
systole/detectors/rolling_average_resp.py
systole/interact/__init__.py
systole/interact/interact.py
systole/plots/__init__.py
systole/plots/plot_circular.py
systole/plots/plot_ectopic.py
systole/plots/plot_events.py
systole/plots/plot_evoked.py
systole/plots/plot_frequency.py
systole/plots/plot_poincare.py
systole/plots/plot_raw.py
systole/plots/plot_rr.py
systole/plots/plot_shortlong.py
systole/plots/plot_subspaces.py
systole/plots/utils.py
systole/plots/backends/__init__.py
systole/plots/backends/bokeh/__init__.py
systole/plots/backends/bokeh/plot_ectopic.py
systole/plots/backends/bokeh/plot_events.py
systole/plots/backends/bokeh/plot_evoked.py
systole/plots/backends/bokeh/plot_frequency.py
systole/plots/backends/bokeh/plot_poincare.py
systole/plots/backends/bokeh/plot_raw.py
systole/plots/backends/bokeh/plot_rr.py
systole/plots/backends/bokeh/plot_shortlong.py
systole/plots/backends/bokeh/plot_subspaces.py
systole/plots/backends/matplotlib/__init__.py
systole/plots/backends/matplotlib/plot_circular.py
systole/plots/backends/matplotlib/plot_ectopic.py
systole/plots/backends/matplotlib/plot_events.py
systole/plots/backends/matplotlib/plot_evoked.py
systole/plots/backends/matplotlib/plot_frequency.py
systole/plots/backends/matplotlib/plot_poincare.py
systole/plots/backends/matplotlib/plot_raw.py
systole/plots/backends/matplotlib/plot_rr.py
systole/plots/backends/matplotlib/plot_shortlong.py
systole/plots/backends/matplotlib/plot_subspaces.py
systole/reports/__init__.py
systole/reports/command_line.py
systole/reports/group_level.html
systole-0.3.0.dist-info/LICENSE
systole-0.3.0.dist-info/METADATA
systole-0.3.0.dist-info/WHEEL
systole-0.3.0.dist-info/entry_points.txt
systole-0.3.0.dist-info/top_level.txt
systole-0.3.0.dist-info/RECORD
