Metadata-Version: 2.1
Name: systole
Version: 0.3.0
Summary: Systole: A python package for cardiac signal synchrony and analysis
Home-page: https://github.com/LegrandNico/systole
Author: Nicolas Legrand
Author-email: nicolas.legrand@cfin.au.dk
Maintainer: Nicolas Legrand
Maintainer-email: nicolas.legrand@cfin.au.dk
License: GPL-3.0
License-File: LICENSE
Requires-Dist: numpy <=1.26,>=1.21
Requires-Dist: scipy >=1.3.0
Requires-Dist: pandas >=0.24
Requires-Dist: matplotlib >=3.0.2
Requires-Dist: seaborn >=0.9.0
Requires-Dist: bokeh >=3.0.0
Requires-Dist: pyserial >=3.4
Requires-Dist: setuptools >=38.4
Requires-Dist: packaging
Requires-Dist: numba >=0.58.0
Requires-Dist: tqdm
Requires-Dist: requests >=2.26.0
Requires-Dist: tabulate >=0.8.9
Requires-Dist: sleepecg >=0.5.1
Requires-Dist: joblib >=1.3.2
